{
    "name" : "Presidents",
    "time" : 3.0,
    "entries" : 44,
    "cols" : ["#", "Name"],
    "fields" : [
        ["1", "George Washington", "George Washington", false],
        ["2", "John Adams", "John Adams", false],
        ["3", "Thomas Jefferson", "Thomas Jefferson", false],
        ["4", "James Madison", "James Madison", false],
        ["5", "James Monroe", "James Monroe", false],
        ["6", "John Quincy Adams", "John Quincy Adams", false],
        ["7", "Andrew Jackson", "Andrew Jackson", false],
        ["8", "Martin Van Buren", "Martin Van Buren", false],
        ["9", "William Henry Harrison", "William Henry Harrison", false],
        ["10", "John Tyler", "John Tyler", false],
        ["11", "James K Polk", "James K Polk", false],
        ["12", "Zachary Taylor", "Zachary Taylor", false],
        ["13", "Millard Filmore", "Millard Filmore", false],
        ["14", "Franklin Pierce", "Franklin Pierce", false],
        ["15", "James Buchanan", "James Buchanan", false],
        ["16", "Abraham Lincoln", "Abraham Lincoln", false],
        ["17", "Andrew Johnson", "Andrew Johnson", false],
        ["18", "Ulysses S Grant", "Ulysses S Grant", false],
        ["19", "Rutherford B Hayes", "Rutherford B Hayes", false],
        ["20", "James A Garfield", "James A Garfield", false],
        ["21", "Chester A Arthur", "Chester A Arthur", false],
        ["22", "Grover Cleveland", "Grover Cleveland", false],
        ["23", "Benjamin Harrison", "Benjamin Harrison", false],
        ["24", "Grover Cleveland", "Grover Cleveland", false],
        ["25", "William McKinley", "William McKinley", false],
        ["26", "Theodore Roosevelt", "Theodore Roosevelt", false],
        ["27", "William Howard Taft", "William Howard Taft", false],
        ["28", "Woodrow Wilson", "Woodrow Wilson", false],
        ["29", "Warren G Harding", "Warren G Harding", false],
        ["30", "Calvin Coolidge", "Calvin Coolidge", false],
        ["31", "Herbert Hoover", "Herbert Hoover", false],
        ["32", "Franklin D Roosevelt", "Franklin D Roosevelt", false],
        ["33", "Harry S Truman", "Harry S Truman", false],
        ["34", "Dwight D Eisenhower", "Dwight D Eisenhower", false],
        ["35", "John F Kennedy", "John F Kennedy", false],
        ["36", "Lyndon B Johnson", "Lyndon B Johnson", false],
        ["37", "Richard Nixon", "Richard Nixon", false],
        ["38", "Gerald Ford", "Gerald Ford", false],
        ["39", "Jimmy Carter", "Jimmy Carter", false],
        ["40", "Ronald Reagan", "Ronald Reagan", false],
        ["41", "George H W Bush", "George H W Bush", false],
        ["42", "Bill Clinton", "Bill Clinton", false],
        ["43", "George W Bush", "George W Bush", false],
        ["44", "Barack Obama", "Barack Obama", false]
        ]
}
